substrateinterface/__init__.py
substrateinterface/base.py
substrateinterface/constants.py
substrateinterface/contracts.py
substrateinterface/exceptions.py
substrateinterface/key.py
substrateinterface/utils/__init__.py
substrateinterface/utils/caching.py
substrateinterface/utils/hasher.py
substrateinterface/utils/ss58.py
test/__init__.py
test/fixtures.py
test/settings.py
test/test_block.py
test/test_contracts.py
test/test_create_extrinsics.py
test/test_helper_functions.py
test/test_init.py
test/test_keypair.py
test/test_query.py
test/test_query_map.py
test/test_ss58.py
test/test_subscriptions.py
test/test_type_registry.py
polymath_substrate_interface-4.0.0.dist-info/LICENSE
polymath_substrate_interface-4.0.0.dist-info/METADATA
polymath_substrate_interface-4.0.0.dist-info/WHEEL
polymath_substrate_interface-4.0.0.dist-info/top_level.txt
polymath_substrate_interface-4.0.0.dist-info/RECORD
